{
  "title": "Recent posts",
  "items": [
    {
      "title": "CrownJewel 1 (HTB-Sherlock)",
      "permalink": "/blog/CrownJewel1-Sherlock",
      "unlisted": false,
      "date": "2025-04-26T00:00:00.000Z"
    },
    {
      "title": "Campfire 2 (HTB-Sherlock)",
      "permalink": "/blog/Campfire2-Sherlock",
      "unlisted": false,
      "date": "2025-04-04T00:00:00.000Z"
    },
    {
      "title": "Campfire 1 (HTB-Sherlock)",
      "permalink": "/blog/Campfire1-Sherlock",
      "unlisted": false,
      "date": "2025-04-03T00:00:00.000Z"
    },
    {
      "title": "Loggy (HTB-Sherlock)",
      "permalink": "/blog/Loggy-Sherlock",
      "unlisted": false,
      "date": "2025-03-19T00:00:00.000Z"
    },
    {
      "title": "What I've Learned - Network Traffic Analysis",
      "permalink": "/blog/NetTrafficAnalysis",
      "unlisted": false,
      "date": "2025-02-03T00:00:00.000Z"
    }
  ]
}